LICENSE
README.md
setup.cfg
setup.py
QFTPy.egg-info/PKG-INFO
QFTPy.egg-info/SOURCES.txt
QFTPy.egg-info/dependency_links.txt
QFTPy.egg-info/requires.txt
QFTPy.egg-info/top_level.txt
qftpy/__init__.py
qftpy/conv.py
qftpy/fft.py
qftpy/io.py
qftpy/utils.py
test/__init__.py
test/_importqftpy.py
test/utils.test.py