Metadata-Version: 2.1
Name: QFTPy
Version: 0.1
Summary: Quaternion Fourier Transform and Convolution
Home-page: https://github.com/z0gSh1u/qftpy
Author: z0gSh1u
Author-email: zx.cs@qq.com
License: MIT
Platform: UNKNOWN
License-File: LICENSE
